agent_sandbox/__init__.py
agent_sandbox/client.py
agent_sandbox/raw_client.py
agent_sandbox/browser/__init__.py
agent_sandbox/browser/client.py
agent_sandbox/browser/raw_client.py
agent_sandbox/browser/types/__init__.py
agent_sandbox/browser/types/action.py
agent_sandbox/code/__init__.py
agent_sandbox/code/client.py
agent_sandbox/code/raw_client.py
agent_sandbox/core/__init__.py
agent_sandbox/core/api_error.py
agent_sandbox/core/client_wrapper.py
agent_sandbox/core/datetime_utils.py
agent_sandbox/core/file.py
agent_sandbox/core/force_multipart.py
agent_sandbox/core/http_client.py
agent_sandbox/core/http_response.py
agent_sandbox/core/jsonable_encoder.py
agent_sandbox/core/pydantic_utilities.py
agent_sandbox/core/query_encoder.py
agent_sandbox/core/remove_none_from_dict.py
agent_sandbox/core/request_options.py
agent_sandbox/core/serialization.py
agent_sandbox/errors/__init__.py
agent_sandbox/errors/unprocessable_entity_error.py
agent_sandbox/file/__init__.py
agent_sandbox/file/client.py
agent_sandbox/file/raw_client.py
agent_sandbox/file/types/__init__.py
agent_sandbox/file/types/command.py
agent_sandbox/jupyter/__init__.py
agent_sandbox/jupyter/client.py
agent_sandbox/jupyter/raw_client.py
agent_sandbox/mcp/__init__.py
agent_sandbox/mcp/client.py
agent_sandbox/mcp/raw_client.py
agent_sandbox/nodejs/__init__.py
agent_sandbox/nodejs/client.py
agent_sandbox/nodejs/raw_client.py
agent_sandbox/providers/__init__.py
agent_sandbox/providers/base.py
agent_sandbox/providers/sign.py
agent_sandbox/providers/volcengine.py
agent_sandbox/sandbox/__init__.py
agent_sandbox/sandbox/client.py
agent_sandbox/sandbox/raw_client.py
agent_sandbox/shell/__init__.py
agent_sandbox/shell/client.py
agent_sandbox/shell/raw_client.py
agent_sandbox/skills/__init__.py
agent_sandbox/skills/client.py
agent_sandbox/skills/raw_client.py
agent_sandbox/types/__init__.py
agent_sandbox/types/action_response.py
agent_sandbox/types/active_sessions_result.py
agent_sandbox-0.0.18.dist-info/METADATA
agent_sandbox-0.0.18.dist-info/WHEEL
agent_sandbox-0.0.18.dist-info/top_level.txt
agent_sandbox-0.0.18.dist-info/RECORD
