Metadata-Version: 2.4
Name: agent-sandbox
Version: 0.0.18
Summary: Python SDK for the All-in-One Sandbox API, >=1.0.0.151
Author: Agent Infra Team
Author-email: "zhengxi.zhou" <zhengxi.zhou@bytedance.com>, jinxin001 <jinxin001@bytedance.com>
License: Apache-2.0
Project-URL: Homepage, https://github.com/agent-infra/sandbox-sdk
Project-URL: Repository, https://github.com/agent-infra/sandbox-sdk
Project-URL: Documentation, https://github.com/agent-infra/sandbox-sdk#readme
Classifier: Development Status :: 4 - Beta
Classifier: Intended Audience :: Developers
Classifier: Programming Language :: Python :: 3
Classifier: Programming Language :: Python :: 3.8
Classifier: Programming Language :: Python :: 3.9
Classifier: Programming Language :: Python :: 3.10
Classifier: Programming Language :: Python :: 3.11
Classifier: Programming Language :: Python :: 3.12
Requires-Python: >=3.8
Requires-Dist: httpx[socks]<1,>=0.23.0
Requires-Dist: pydantic<3,>=1.9.0
Requires-Dist: typing_extensions>=4.0.0; python_version < "3.10"
Requires-Dist: volcengine-python-sdk>=4.0.17
Dynamic: author
Dynamic: requires-python
